cli/__init__.py
cli/commons/__init__.py
cli/commons/decorators.py
cli/commons/enums.py
cli/commons/exceptions.py
cli/commons/models.py
cli/commons/pipelines.py
cli/commons/styles.py
cli/commons/utils.py
cli/commons/utils_tests.py
cli/commons/validators.py
cli/compat.py
cli/config/__init__.py
cli/config/commands.py
cli/config/handlers.py
cli/config/helpers.py
cli/config/models.py
cli/config/tests/__init__.py
cli/config/tests/test_commands.py
cli/config/tests/test_helpers.py
cli/devices/__init__.py
cli/devices/commands.py
cli/devices/handlers.py
cli/devices/helpers.py
cli/devices/tests/__init__.py
cli/devices/tests/test_commands.py
cli/functions/__init__.py
cli/functions/commands.py
cli/functions/engines/__init__.py
cli/functions/engines/abstracts/__init__.py
cli/functions/engines/abstracts/client.py
cli/functions/engines/abstracts/container.py
cli/functions/engines/abstracts/image.py
cli/functions/engines/abstracts/network.py
cli/functions/engines/abstracts/validators.py
cli/functions/engines/docker/__init__.py
cli/functions/engines/docker/client.py
cli/functions/engines/docker/container.py
cli/functions/engines/docker/image.py
cli/functions/engines/docker/models.py
cli/functions/engines/docker/network.py
cli/functions/engines/docker/validators.py
cli/functions/engines/enums.py
cli/functions/engines/exceptions.py
cli/functions/engines/manager.py
cli/functions/engines/models.py
cli/functions/engines/podman/__init__.py
cli/functions/engines/podman/client.py
cli/functions/engines/podman/container.py
cli/functions/engines/podman/image.py
cli/functions/engines/podman/network.py
cli/functions/engines/podman/validators.py
cli/functions/engines/settings.py
cli/functions/engines/tests/__init__.py
cli/functions/engines/tests/test_models.py
cli/functions/enums.py
cli/functions/exceptions.py
cli/functions/executor.py
cli/functions/handlers.py
cli/functions/helpers.py
cli/functions/lambda_handlers/__init__.py
cli/functions/lambda_handlers/handler.mjs
ubidots_cli-0.2.0.dist-info/METADATA
ubidots_cli-0.2.0.dist-info/WHEEL
ubidots_cli-0.2.0.dist-info/entry_points.txt
ubidots_cli-0.2.0.dist-info/RECORD
