Metadata-Version: 2.3
Name: ubidots-cli
Version: 0.2.0
Summary: A powerful CLI tool for efficient management and automation of cloud-based resources.
Author: Ubidots
Author-email: devel@ubidots.com
Requires-Python: >=3.9,<3.13
Classifier: Programming Language :: Python :: 3
Classifier: Programming Language :: Python :: 3.9
Classifier: Programming Language :: Python :: 3.10
Classifier: Programming Language :: Python :: 3.11
Classifier: Programming Language :: Python :: 3.12
Provides-Extra: simplification
Requires-Dist: croniter (>=2.0.1,<3.0.0)
Requires-Dist: docker (>=7.0.0,<8.0.0)
Requires-Dist: httpx (>=0.27.0,<0.28.0)
Requires-Dist: inquirerpy (>=0.3.4,<0.4.0)
Requires-Dist: podman (>=4.9.0,<5.0.0)
Requires-Dist: pydantic (>=2.5.3,<3.0.0)
Requires-Dist: pydantic-settings (>=2.1.0,<3.0.0)
Requires-Dist: pyyaml (>=6.0.1,<7.0.0)
Requires-Dist: requests (>=2.31.0,<3.0.0)
Requires-Dist: rich (>=13.7.0,<14.0.0)
Requires-Dist: typer (>=0.9.0,<0.10.0)
